rag_core_api/api_endpoints/__init__.py
rag_core_api/api_endpoints/chat.py
rag_core_api/api_endpoints/information_piece_remover.py
rag_core_api/api_endpoints/information_piece_uploader.py
rag_core_api/apis/__init__.py
rag_core_api/apis/rag_api.py
rag_core_api/apis/rag_api_base.py
rag_core_api/dependency_container.py
rag_core_api/embeddings/__init__.py
rag_core_api/embeddings/embedder.py
rag_core_api/evaluator/__init__.py
rag_core_api/evaluator/evaluator.py
rag_core_api/graph/__init__.py
rag_core_api/graph/graph_base.py
rag_core_api/impl/__init__.py
rag_core_api/impl/answer_generation_chains/__init__.py
rag_core_api/impl/answer_generation_chains/answer_generation_chain.py
rag_core_api/impl/answer_generation_chains/language_detection_chain.py
rag_core_api/impl/answer_generation_chains/rephrasing_chain.py
rag_core_api/impl/api_endpoints/__init__.py
rag_core_api/impl/api_endpoints/default_chat.py
rag_core_api/impl/api_endpoints/default_information_pieces_remover.py
rag_core_api/impl/api_endpoints/default_information_pieces_uploader.py
rag_core_api/impl/embeddings/__init__.py
rag_core_api/impl/embeddings/embedder_type.py
rag_core_api/impl/embeddings/langchain_community_embedder.py
rag_core_api/impl/embeddings/stackit_embedder.py
rag_core_api/impl/evaluator/__init__.py
rag_core_api/impl/evaluator/langfuse_ragas_evaluator.py
rag_core_api/impl/graph/__init__.py
rag_core_api/impl/graph/chat_graph.py
rag_core_api/impl/graph/graph_state/__init__.py
rag_core_api/impl/graph/graph_state/graph_state.py
rag_core_api/impl/rag_api.py
rag_core_api/impl/reranking/__init__.py
rag_core_api/impl/reranking/flashrank_reranker.py
rag_core_api/impl/retriever/__init__.py
rag_core_api/impl/retriever/composite_retriever.py
rag_core_api/impl/retriever/no_or_empty_collection_error.py
rag_core_api/impl/retriever/retriever_quark.py
rag_core_api/impl/settings/__init__.py
rag_core_api/impl/settings/chat_history_settings.py
rag_core_api/impl/settings/embedder_class_type_settings.py
rag_core_api-3.4.0.dist-info/METADATA
rag_core_api-3.4.0.dist-info/WHEEL
rag_core_api-3.4.0.dist-info/RECORD
