Metadata-Version: 2.4
Name: rag-core-api
Version: 3.4.0
Summary: The rag-core-api contains the API layer for the RAG template for document retrieval, question answering, knowledge base management in the vector database and more.
License: Apache-2.0
Author: STACKIT GmbH & Co. KG
Author-email: data-ai@stackit.cloud
Maintainer: Andreas Klos
Maintainer-email: andreas.klos@stackit.cloud
Requires-Python: >=3.13,<4.0
Classifier: License :: OSI Approved :: Apache Software License
Classifier: Programming Language :: Python :: 3
Classifier: Programming Language :: Python :: 3.13
Classifier: Programming Language :: Python :: 3.14
Requires-Dist: datasets (>=3.5.1,<4.0.0)
Requires-Dist: dependency-injector (>=4.46.0,<5.0.0)
Requires-Dist: deprecated (>=1.2.18,<2.0.0)
Requires-Dist: fastapi (>=0.118.0,<0.119.0)
Requires-Dist: fastembed (>=0.7.0,<0.8.0)
Requires-Dist: flashrank (>=0.2.10,<0.3.0)
Requires-Dist: langchain-community (==0.3.30)
Requires-Dist: langchain-ollama (>=0.3.2,<0.4.0)
Requires-Dist: langchain-qdrant (>=0.2.0,<0.3.0)
Requires-Dist: langchain-text-splitters (>=0.3.9)
Requires-Dist: langdetect (>=1.0.9,<2.0.0)
Requires-Dist: langfuse (==3.6.1)
Requires-Dist: langgraph (>=0.6.0,<0.7.0)
Requires-Dist: openai (>=1.77.0,<2.0.0)
Requires-Dist: pillow (>=11.2.1,<12.0.0)
Requires-Dist: pytest-asyncio (>=0.26.0,<0.27.0)
Requires-Dist: pyyaml (>=6.0.2,<7.0.0)
Requires-Dist: qdrant-client (>=1.14.2,<2.0.0)
Requires-Dist: rag-core-lib (==3.4.0)
Requires-Dist: ragas (>=0.3.0,<0.4.0)
Requires-Dist: requests-oauthlib (>=2.0.0,<3.0.0)
Requires-Dist: uvicorn (>=0.37.0,<0.38.0)
Project-URL: Homepage, https://pypi.org/project/rag-core-api
Project-URL: Repository, https://github.com/stackitcloud/rag-template
